{
  "id": "483134cb-52d2-4685-9942-a8adbe48d705",
  "prevId": "691a2fcd-4dda-4fe0-ac3b-668d09ce3cfb",
  "version": "7",
  "dialect": "postgresql",
  "tables": {
    "public.custom_metrics": {
      "name": "custom_metrics",
      "schema": "",
      "columns": {
        "id": {
          "name": "id",
          "type": "serial",
          "primaryKey": true,
          "notNull": true
        },
        "user_id": {
          "name": "user_id",
          "type": "integer",
          "primaryKey": false,
          "notNull": true
        },
        "name": {
          "name": "name",
          "type": "text",
          "primaryKey": false,
          "notNull": true
        },
        "description": {
          "name": "description",
          "type": "text",
          "primaryKey": false,
          "notNull": false
        },
        "emoji": {
          "name": "emoji",
          "type": "text",
          "primaryKey": false,
          "notNull": false,
          "default": "'⭐'"
        },
        "sort_order": {
          "name": "sort_order",
          "type": "integer",
          "primaryKey": false,
          "notNull": false,
          "default": 0
        },
        "is_active": {
          "name": "is_active",
          "type": "boolean",
          "primaryKey": false,
          "notNull": false,
          "default": true
        }
      },
      "indexes": {},
      "foreignKeys": {},
      "compositePrimaryKeys": {},
      "uniqueConstraints": {},
      "policies": {},
      "checkConstraints": {},
      "isRLSEnabled": false
    },
    "public.daily_entries": {
      "name": "daily_entries",
      "schema": "",
      "columns": {
        "id": {
          "name": "id",
          "type": "serial",
          "primaryKey": true,
          "notNull": true
        },
        "user_id": {
          "name": "user_id",
          "type": "integer",
          "primaryKey": false,
          "notNull": true
        },
        "entry_date": {
          "name": "entry_date",
          "type": "date",
          "primaryKey": false,
          "notNull": true
        },
        "notes": {
          "name": "notes",
          "type": "text",
          "primaryKey": false,
          "notNull": false
        },
        "created_at": {
          "name": "created_at",
          "type": "timestamp",
          "primaryKey": false,
          "notNull": true,
          "default": "now()"
        },
        "updated_at": {
          "name": "updated_at",
          "type": "timestamp",
          "primaryKey": false,
          "notNull": true,
          "default": "now()"
        }
      },
      "indexes": {},
      "foreignKeys": {},
      "compositePrimaryKeys": {},
      "uniqueConstraints": {},
      "policies": {},
      "checkConstraints": {},
      "isRLSEnabled": false
    },
    "public.metric_scores": {
      "name": "metric_scores",
      "schema": "",
      "columns": {
        "id": {
          "name": "id",
          "type": "serial",
          "primaryKey": true,
          "notNull": true
        },
        "entry_id": {
          "name": "entry_id",
          "type": "integer",
          "primaryKey": false,
          "notNull": true
        },
        "user_id": {
          "name": "user_id",
          "type": "integer",
          "primaryKey": false,
          "notNull": true
        },
        "metric_key": {
          "name": "metric_key",
          "type": "text",
          "primaryKey": false,
          "notNull": true
        },
        "metric_label": {
          "name": "metric_label",
          "type": "text",
          "primaryKey": false,
          "notNull": true
        },
        "rating": {
          "name": "rating",
          "type": "text",
          "primaryKey": false,
          "notNull": true
        }
      },
      "indexes": {},
      "foreignKeys": {},
      "compositePrimaryKeys": {},
      "uniqueConstraints": {},
      "policies": {},
      "checkConstraints": {},
      "isRLSEnabled": false
    },
    "public.password_reset_tokens": {
      "name": "password_reset_tokens",
      "schema": "",
      "columns": {
        "id": {
          "name": "id",
          "type": "serial",
          "primaryKey": true,
          "notNull": true
        },
        "user_id": {
          "name": "user_id",
          "type": "integer",
          "primaryKey": false,
          "notNull": true
        },
        "token": {
          "name": "token",
          "type": "text",
          "primaryKey": false,
          "notNull": true
        },
        "expires_at": {
          "name": "expires_at",
          "type": "timestamp",
          "primaryKey": false,
          "notNull": true
        },
        "used_at": {
          "name": "used_at",
          "type": "timestamp",
          "primaryKey": false,
          "notNull": false
        },
        "created_at": {
          "name": "created_at",
          "type": "timestamp",
          "primaryKey": false,
          "notNull": true,
          "default": "now()"
        }
      },
      "indexes": {},
      "foreignKeys": {},
      "compositePrimaryKeys": {},
      "uniqueConstraints": {
        "password_reset_tokens_token_unique": {
          "name": "password_reset_tokens_token_unique",
          "nullsNotDistinct": false,
          "columns": [
            "token"
          ]
        }
      },
      "policies": {},
      "checkConstraints": {},
      "isRLSEnabled": false
    },
    "public.subscriptions": {
      "name": "subscriptions",
      "schema": "",
      "columns": {
        "id": {
          "name": "id",
          "type": "serial",
          "primaryKey": true,
          "notNull": true
        },
        "user_id": {
          "name": "user_id",
          "type": "integer",
          "primaryKey": false,
          "notNull": true
        },
        "stripe_customer_id": {
          "name": "stripe_customer_id",
          "type": "text",
          "primaryKey": false,
          "notNull": false
        },
        "stripe_subscription_id": {
          "name": "stripe_subscription_id",
          "type": "text",
          "primaryKey": false,
          "notNull": false
        },
        "stripe_price_id": {
          "name": "stripe_price_id",
          "type": "text",
          "primaryKey": false,
          "notNull": false
        },
        "plan": {
          "name": "plan",
          "type": "text",
          "primaryKey": false,
          "notNull": false,
          "default": "'free'"
        },
        "status": {
          "name": "status",
          "type": "text",
          "primaryKey": false,
          "notNull": false,
          "default": "'inactive'"
        },
        "current_period_end": {
          "name": "current_period_end",
          "type": "timestamp",
          "primaryKey": false,
          "notNull": false
        },
        "updated_at": {
          "name": "updated_at",
          "type": "timestamp",
          "primaryKey": false,
          "notNull": true,
          "default": "now()"
        }
      },
      "indexes": {},
      "foreignKeys": {},
      "compositePrimaryKeys": {},
      "uniqueConstraints": {
        "subscriptions_user_id_unique": {
          "name": "subscriptions_user_id_unique",
          "nullsNotDistinct": false,
          "columns": [
            "user_id"
          ]
        }
      },
      "policies": {},
      "checkConstraints": {},
      "isRLSEnabled": false
    },
    "public.user_schedule": {
      "name": "user_schedule",
      "schema": "",
      "columns": {
        "id": {
          "name": "id",
          "type": "serial",
          "primaryKey": true,
          "notNull": true
        },
        "user_id": {
          "name": "user_id",
          "type": "integer",
          "primaryKey": false,
          "notNull": true
        },
        "wake_time": {
          "name": "wake_time",
          "type": "text",
          "primaryKey": false,
          "notNull": false,
          "default": "'06:00'"
        },
        "sleep_time": {
          "name": "sleep_time",
          "type": "text",
          "primaryKey": false,
          "notNull": false,
          "default": "'22:00'"
        },
        "work_start_time": {
          "name": "work_start_time",
          "type": "text",
          "primaryKey": false,
          "notNull": false,
          "default": "'09:00'"
        },
        "work_end_time": {
          "name": "work_end_time",
          "type": "text",
          "primaryKey": false,
          "notNull": false,
          "default": "'17:00'"
        },
        "timezone": {
          "name": "timezone",
          "type": "text",
          "primaryKey": false,
          "notNull": false,
          "default": "'America/New_York'"
        },
        "daily_goal": {
          "name": "daily_goal",
          "type": "text",
          "primaryKey": false,
          "notNull": false
        },
        "updated_at": {
          "name": "updated_at",
          "type": "timestamp",
          "primaryKey": false,
          "notNull": true,
          "default": "now()"
        }
      },
      "indexes": {},
      "foreignKeys": {},
      "compositePrimaryKeys": {},
      "uniqueConstraints": {
        "user_schedule_user_id_unique": {
          "name": "user_schedule_user_id_unique",
          "nullsNotDistinct": false,
          "columns": [
            "user_id"
          ]
        }
      },
      "policies": {},
      "checkConstraints": {},
      "isRLSEnabled": false
    },
    "public.users": {
      "name": "users",
      "schema": "",
      "columns": {
        "id": {
          "name": "id",
          "type": "serial",
          "primaryKey": true,
          "notNull": true
        },
        "email": {
          "name": "email",
          "type": "text",
          "primaryKey": false,
          "notNull": true
        },
        "username": {
          "name": "username",
          "type": "text",
          "primaryKey": false,
          "notNull": true
        },
        "password": {
          "name": "password",
          "type": "text",
          "primaryKey": false,
          "notNull": true
        },
        "display_name": {
          "name": "display_name",
          "type": "text",
          "primaryKey": false,
          "notNull": true
        },
        "created_at": {
          "name": "created_at",
          "type": "timestamp",
          "primaryKey": false,
          "notNull": true,
          "default": "now()"
        }
      },
      "indexes": {},
      "foreignKeys": {},
      "compositePrimaryKeys": {},
      "uniqueConstraints": {
        "users_email_unique": {
          "name": "users_email_unique",
          "nullsNotDistinct": false,
          "columns": [
            "email"
          ]
        },
        "users_username_unique": {
          "name": "users_username_unique",
          "nullsNotDistinct": false,
          "columns": [
            "username"
          ]
        }
      },
      "policies": {},
      "checkConstraints": {},
      "isRLSEnabled": false
    }
  },
  "enums": {},
  "schemas": {},
  "sequences": {},
  "roles": {},
  "policies": {},
  "views": {},
  "_meta": {
    "columns": {},
    "schemas": {},
    "tables": {}
  }
}